browser7/__init__.py
browser7/py.typed
browser7-0.1.0a1.dist-info/licenses/LICENSE
browser7-0.1.0a1.dist-info/METADATA
browser7-0.1.0a1.dist-info/WHEEL
browser7-0.1.0a1.dist-info/top_level.txt
browser7-0.1.0a1.dist-info/RECORD
