Metadata-Version: 2.4
Name: browser7
Version: 0.1.0a1
Summary: Official Python SDK for Browser7 - Geo-targeted web scraping with automatic CAPTCHA solving and wait actions [ALPHA - API launching Q2 2026]
Author-email: Browser7 <support@browser7.com>
License: MIT
Project-URL: Homepage, https://browser7.com
Project-URL: Documentation, https://docs.browser7.com
Project-URL: Repository, https://github.com/browser7data/browser7-python
Project-URL: Bug Tracker, https://github.com/browser7data/browser7-python/issues
Keywords: browser7,web-scraping,scraping,rendering,headless-browser,captcha,captcha-solver,geo-targeting,proxy,api-client,screenshot,automation
Classifier: Development Status :: 3 - Alpha
Classifier: Intended Audience :: Developers
Classifier: License :: OSI Approved :: MIT License
Classifier: Programming Language :: Python :: 3
Classifier: Programming Language :: Python :: 3.8
Classifier: Programming Language :: Python :: 3.9
Classifier: Programming Language :: Python :: 3.10
Classifier: Programming Language :: Python :: 3.11
Classifier: Programming Language :: Python :: 3.12
Classifier: Topic :: Internet :: WWW/HTTP
Classifier: Topic :: Software Development :: Libraries :: Python Modules
Requires-Python: >=3.8
License-File: LICENSE
Dynamic: license-file
